saas_core_lib/__init__.py
saas_core_lib/config.py
saas_core_lib/database.py
saas_core_lib/elasticsearch.py
saas_core_lib/redis_client.py
saas_core_lib/security.py
saas_core_lib/logging/__init__.py
saas_core_lib/logging/logger.py
saas_core_lib/response/__init__.py
saas_core_lib/response/error.json
saas_core_lib/response/error.md
saas_core_lib/response/error.yaml
saas_core_lib/response/response_handler.py
saas_core_lib/response/success.json
saas_core_lib/response/success.md
saas_core_lib-0.1.5.dist-info/licenses/LICENSE
saas_core_lib-0.1.5.dist-info/METADATA
saas_core_lib-0.1.5.dist-info/WHEEL
saas_core_lib-0.1.5.dist-info/top_level.txt
saas_core_lib-0.1.5.dist-info/RECORD
