Metadata-Version: 2.4
Name: saas-core-lib
Version: 0.1.5
Summary: Common core library for all microservices
Author-email: Hasan Bahadır <hasan@hashub.dev>
Project-URL: Homepage, https://github.com/hasanbahadir/saas-core-lib
Project-URL: Bug Reports, https://github.com/hasanbahadir/saas-core-lib/issues
Project-URL: Source, https://github.com/hasanbahadir/saas-core-lib
Classifier: Development Status :: 4 - Beta
Classifier: Intended Audience :: Developers
Classifier: License :: OSI Approved :: MIT License
Classifier: Programming Language :: Python :: 3
Classifier: Programming Language :: Python :: 3.10
Classifier: Programming Language :: Python :: 3.11
Classifier: Programming Language :: Python :: 3.12
Classifier: Framework :: FastAPI
Classifier: Topic :: Software Development :: Libraries :: Python Modules
Requires-Python: >=3.10
License-File: LICENSE
Requires-Dist: fastapi>=0.104.0
Requires-Dist: pydantic>=2.0.0
Requires-Dist: pydantic-settings>=2.0.0
Requires-Dist: sqlalchemy>=2.0.0
Requires-Dist: alembic>=1.12.0
Requires-Dist: asyncpg>=0.28.0
Requires-Dist: psycopg2-binary>=2.9.0
Requires-Dist: elasticsearch>=8.0.0
Requires-Dist: redis>=4.5.0
Requires-Dist: passlib>=1.7.0
Requires-Dist: bcrypt>=4.0.0
Requires-Dist: python-jose>=3.3.0
Requires-Dist: cryptography>=41.0.0
Requires-Dist: structlog>=23.0.0
Requires-Dist: httpx>=0.25.0
Requires-Dist: python-multipart>=0.0.6
Requires-Dist: email-validator>=2.0.0
Provides-Extra: dev
Requires-Dist: pytest>=7.4.0; extra == "dev"
Requires-Dist: pytest-asyncio>=0.21.0; extra == "dev"
Requires-Dist: pytest-cov>=4.1.0; extra == "dev"
Requires-Dist: black>=23.0.0; extra == "dev"
Requires-Dist: isort>=5.12.0; extra == "dev"
Requires-Dist: flake8>=6.0.0; extra == "dev"
Requires-Dist: mypy>=1.5.0; extra == "dev"
Requires-Dist: pre-commit>=3.4.0; extra == "dev"
Provides-Extra: unix
Requires-Dist: uvloop>=0.17.0; extra == "unix"
Dynamic: license-file
